mcp_vultr/__init__.py
mcp_vultr/__main__.py
mcp_vultr/_version.py
mcp_vultr/api_key_broker.py
mcp_vultr/backups.py
mcp_vultr/bare_metal.py
mcp_vultr/billing.py
mcp_vultr/billing_analyzer.py
mcp_vultr/block_storage.py
mcp_vultr/cache.py
mcp_vultr/cdn.py
mcp_vultr/cdn_analyzer.py
mcp_vultr/cli_main.py
mcp_vultr/client.py
mcp_vultr/container_registry.py
mcp_vultr/database_analyzer.py
mcp_vultr/dns.py
mcp_vultr/dns_analyzer.py
mcp_vultr/fastmcp_server.py
mcp_vultr/firewall.py
mcp_vultr/instances.py
mcp_vultr/iso.py
mcp_vultr/kubernetes.py
mcp_vultr/kubernetes_analyzer.py
mcp_vultr/load_balancer.py
mcp_vultr/load_balancer_analyzer.py
mcp_vultr/managed_databases.py
mcp_vultr/marketplace.py
mcp_vultr/metrics.py
mcp_vultr/notification_manager.py
mcp_vultr/oauth_auth.py
mcp_vultr/oauth_server.py
mcp_vultr/object_storage.py
mcp_vultr/object_storage_analyzer.py
mcp_vultr/os.py
mcp_vultr/plans.py
mcp_vultr/py.typed
mcp_vultr/regions.py
mcp_vultr/reserved_ips.py
mcp_vultr/retry.py
mcp_vultr/server.py
mcp_vultr/serverless_inference.py
mcp_vultr/serverless_inference_analyzer.py
mcp_vultr/service_collections.py
mcp_vultr/snapshots.py
mcp_vultr/ssh_keys.py
mcp_vultr/startup_scripts.py
mcp_vultr/storage_gateways.py
mcp_vultr/subaccount.py
mcp_vultr/tui_app.py
mcp_vultr/users.py
mcp_vultr/vpcs.py
mcp_vultr/vultr_logging.py
mcp_vultr/cli/__init__.py
mcp_vultr/cli/billing.py
mcp_vultr/cli/compute.py
mcp_vultr/cli/dns.py
mcp_vultr/cli/service_collections.py
mcp_vultr/cli/utils.py
mcp_vultr-2.2.7.dist-info/licenses/LICENSE
mcp_vultr-2.2.7.dist-info/METADATA
mcp_vultr-2.2.7.dist-info/WHEEL
mcp_vultr-2.2.7.dist-info/entry_points.txt
mcp_vultr-2.2.7.dist-info/top_level.txt
mcp_vultr-2.2.7.dist-info/RECORD
