Metadata-Version: 2.4
Name: mcp-vultr
Version: 2.2.7
Summary: A comprehensive Model Context Protocol (MCP) server for managing Vultr DNS records
Author-email: Ryan Malloy <ryan@supported.systems>
Maintainer-email: Ryan Malloy <ryan@supported.systems>
License: MIT
Project-URL: Homepage, https://git.supported.systems/MCP/mcp-vultr
Project-URL: Documentation, https://mcp-vultr.readthedocs.io/
Project-URL: Repository, https://git.supported.systems/MCP/mcp-vultr.git
Project-URL: Bug Tracker, https://git.supported.systems/MCP/mcp-vultr/issues
Project-URL: Changelog, https://git.supported.systems/MCP/mcp-vultr/blob/main/CHANGELOG.md
Keywords: vultr,dns,mcp,model-context-protocol,dns-management,api,mcp-server
Classifier: Development Status :: 5 - Production/Stable
Classifier: Intended Audience :: Developers
Classifier: Intended Audience :: System Administrators
Classifier: License :: OSI Approved :: MIT License
Classifier: Operating System :: OS Independent
Classifier: Programming Language :: Python :: 3
Classifier: Programming Language :: Python :: 3.10
Classifier: Programming Language :: Python :: 3.11
Classifier: Programming Language :: Python :: 3.12
Classifier: Programming Language :: Python :: 3.13
Classifier: Topic :: Internet :: Name Service (DNS)
Classifier: Topic :: System :: Systems Administration
Classifier: Topic :: Software Development :: Libraries :: Python Modules
Classifier: Topic :: Communications
Classifier: Environment :: Console
Classifier: Framework :: AsyncIO
Requires-Python: >=3.11
License-File: LICENSE
Requires-Dist: fastmcp>=0.1.0
Requires-Dist: httpx>=0.24.0
Requires-Dist: httpcore>=1.0.0
Requires-Dist: pydantic>=2.0.0
Requires-Dist: click>=8.0.0
Requires-Dist: structlog>=23.0.0
Requires-Dist: tenacity>=8.0.0
Requires-Dist: cachetools>=5.0.0
Requires-Dist: psutil>=6.0.0
Requires-Dist: textual>=0.45.0
Requires-Dist: rich>=13.0.0
Requires-Dist: pyjwt[crypto]>=2.8.0
Provides-Extra: dev
Requires-Dist: pytest>=7.0.0; extra == "dev"
Requires-Dist: pytest-asyncio>=0.21.0; extra == "dev"
Requires-Dist: pytest-textual-snapshot>=0.4.0; extra == "dev"
Requires-Dist: pytest-cov>=4.0.0; extra == "dev"
Requires-Dist: pytest-xdist>=3.0.0; extra == "dev"
Requires-Dist: pytest-timeout>=2.1.0; extra == "dev"
Requires-Dist: pytest-mock>=3.10.0; extra == "dev"
Requires-Dist: pytest-textual-snapshot>=0.4.0; extra == "dev"
Requires-Dist: ruff>=0.1.14; extra == "dev"
Requires-Dist: mypy>=1.0.0; extra == "dev"
Requires-Dist: pre-commit>=3.0.0; extra == "dev"
Requires-Dist: rich>=13.0.0; extra == "dev"
Requires-Dist: bandit>=1.7.0; extra == "dev"
Requires-Dist: safety>=3.0.0; extra == "dev"
Provides-Extra: docs
Requires-Dist: sphinx>=6.0.0; extra == "docs"
Requires-Dist: sphinx-rtd-theme>=1.2.0; extra == "docs"
Requires-Dist: myst-parser>=1.0.0; extra == "docs"
Provides-Extra: test
Requires-Dist: pytest>=7.0.0; extra == "test"
Requires-Dist: pytest-asyncio>=0.21.0; extra == "test"
Requires-Dist: pytest-cov>=4.0.0; extra == "test"
Requires-Dist: pytest-httpx>=0.21.0; extra == "test"
Requires-Dist: pytest-xdist>=3.0.0; extra == "test"
Requires-Dist: pytest-timeout>=2.1.0; extra == "test"
Requires-Dist: pytest-mock>=3.10.0; extra == "test"
Requires-Dist: pytest-textual-snapshot>=0.4.0; extra == "test"
Dynamic: license-file
